ip_country/__init__.py
ip_country/ip_country.py
ip_country/ip_country_test.py
ip_country-1.0.0.dist-info/LICENSE
ip_country-1.0.0.dist-info/METADATA
ip_country-1.0.0.dist-info/WHEEL
ip_country-1.0.0.dist-info/top_level.txt
ip_country-1.0.0.dist-info/RECORD
