Metadata-Version: 2.1
Name: ip-country
Version: 1.0.0
Summary: An offline tool to get country by IP
Home-page: https://github.com/dmitriiweb/ip-country
Author: Dmitrii K
Author-email: winston.smith.spb@gmail.com
License: MIT
Platform: UNKNOWN
Classifier: Development Status :: 5 - Production/Stable
Classifier: Intended Audience :: Developers
Classifier: License :: OSI Approved :: MIT License
Classifier: Programming Language :: Python
Classifier: Programming Language :: Python :: 3.6
Requires-Dist: pandas (>=0.25.0)
